django_settingsdict/__init__.py
django_settingsdict-1.1.1.dist-info/LICENSE
django_settingsdict-1.1.1.dist-info/METADATA
django_settingsdict-1.1.1.dist-info/WHEEL
django_settingsdict-1.1.1.dist-info/top_level.txt
django_settingsdict-1.1.1.dist-info/RECORD
