Metadata-Version: 2.1
Name: django-settingsdict
Version: 1.1.1
Summary: Simple helper class to handle dict style settings for django app
Home-page: https://github.com/raphendyr/django-settingsdict
Author: Jaakko Kantojärvi
Author-email: jaakko@n-1.fi
License: BSD
Download-URL: https://github.com/raphendyr/django-settingsdict/archive/1.1.1.tar.gz
Keywords: django settings
Platform: UNKNOWN
Classifier: Development Status :: 4 - Beta
Classifier: License :: OSI Approved :: BSD License
Classifier: Intended Audience :: Developers
Classifier: Environment :: Web Environment
Classifier: Operating System :: OS Independent
Classifier: Topic :: Software Development :: Build Tools
Classifier: Topic :: Software Development :: Libraries :: Python Modules
Classifier: Framework :: Django
Classifier: Framework :: Django :: 1.8
Classifier: Framework :: Django :: 1.9
Classifier: Programming Language :: Python :: 2
Classifier: Programming Language :: Python :: 2.7
Classifier: Programming Language :: Python :: 3
Classifier: Programming Language :: Python :: 3.4
Classifier: Programming Language :: Python :: 3.5
Requires-Dist: Django (>=1.8)
